DESCRIPTION
MANIFEST.in
README
README.rst
setup.py
attachment/__init__.py
attachment/__init__.pyc
attachment/admin.py
attachment/fields.py
attachment/forms.py
attachment/ikspecs.py
attachment/importpath.py
attachment/models.py
attachment/settings.py
attachment/urls.py
attachment/views.py
attachment/widgets.py
attachment/migrations/0001_initial.py
attachment/migrations/0002_auto__add_field_attachmentimage_title__add_field_attachmentfile_title.py
attachment/migrations/0003_auto__add_field_attachmentimage_position__add_field_attachmentfile_pos.py
attachment/migrations/0004_auto__chg_field_attachmentimage_title.py
attachment/migrations/0005_auto__add_field_attachmentimage_group.py
attachment/migrations/0006_change_char_field_on_text_field.py
attachment/migrations/__init__.py
attachment/redsolution_setup/__init__.py
attachment/redsolution_setup/admin.py
attachment/redsolution_setup/make.py
attachment/redsolution_setup/models.py
attachment/redsolution_setup/templates/attachment/redsolutioncms/settings.pyt
attachment/redsolution_setup/templates/attachment/redsolutioncms/urls.pyt
attachment/templates/attachment/show.html
attachment/templatetags/__init__.py
attachment/templatetags/attachment_tags.py
redsolutioncms.django_tinymce_attachment.egg-info/PKG-INFO
redsolutioncms.django_tinymce_attachment.egg-info/SOURCES.txt
redsolutioncms.django_tinymce_attachment.egg-info/dependency_links.txt
redsolutioncms.django_tinymce_attachment.egg-info/entry_points.txt
redsolutioncms.django_tinymce_attachment.egg-info/not-zip-safe
redsolutioncms.django_tinymce_attachment.egg-info/requires.txt
redsolutioncms.django_tinymce_attachment.egg-info/top_level.txt