Metadata-Version: 1.1
Name: redsolutioncms.django-tinymce-attachment
Version: 0.5.0
Summary: Allows to attach files and images for any objects, specified in configuration.
Home-page: UNKNOWN
Author: Alexander Ivanov
Author-email: alexander.ivanov@redsolution.ru
License: GPLv3
Keywords: django tinymce attachment
Platform: UNKNOWN
Classifier: Development Status :: 3 - Alpha
Classifier: Intended Audience :: Developers
Classifier: License :: OSI Approved :: GNU General Public License (GPL)
Classifier: Framework :: Django
Classifier: Environment :: Web Environment
Classifier: Natural Language :: Russian
Classifier: Natural Language :: English
Classifier: Operating System :: OS Independent
Classifier: Programming Language :: Python
Classifier: Topic :: Internet :: WWW/HTTP :: Site Management
